riot_observer/__init__.py
riot_observer/constants.py
riot_observer/observer.py
riot_observer-1.3.3.dist-info/DESCRIPTION.rst
riot_observer-1.3.3.dist-info/METADATA
riot_observer-1.3.3.dist-info/RECORD
riot_observer-1.3.3.dist-info/WHEEL
riot_observer-1.3.3.dist-info/metadata.json
riot_observer-1.3.3.dist-info/top_level.txt
