Metadata-Version: 2.0
Name: riot-observer
Version: 1.3.3
Summary: Python light wrapper for the Riot Games API for League of Legends
Home-page: https://github.com/Darquiche/Riot-Observer
Author: Darqi
Author-email: UNKNOWN
License: MIT
Keywords: league of legends riot games api wrapper development python
Platform: UNKNOWN
Classifier: Programming Language :: Python
Classifier: Development Status :: 4 - Beta
Classifier: License :: OSI Approved :: MIT License
Classifier: Natural Language :: English
Classifier: Operating System :: OS Independent
Classifier: Topic :: Software Development :: Libraries :: Python Modules
Classifier: Topic :: Text Processing
Classifier: Topic :: Games/Entertainment :: Real Time Strategy
Classifier: Topic :: Games/Entertainment :: Role-Playing
Requires-Dist: requests
